jiramd/__init__.py
jiramd/code.py
jiramd/extension.py
jiramd/link.py
jiramd/monospace.py
jira_wiki_md-0.5.0.dist-info/METADATA
jira_wiki_md-0.5.0.dist-info/WHEEL
jira_wiki_md-0.5.0.dist-info/entry_points.txt
jira_wiki_md-0.5.0.dist-info/top_level.txt
jira_wiki_md-0.5.0.dist-info/RECORD
