Metadata-Version: 2.1
Name: jira-wiki-md
Version: 0.5.0
Summary: UNKNOWN
Home-page: UNKNOWN
Author: Jean Giard
Author-email: UNKNOWN
License: LGPL
Platform: UNKNOWN
Requires-Dist: markdown
